otsun/__init__.py
otsun/data/ASTMG173-direct.txt
otsun/experiments.py
otsun/helpers.py
otsun/materials.py
otsun/math.py
otsun/movements.py
otsun/optics.py
otsun/outputs.py
otsun/ray.py
otsun/scene.py
otsun/source.py
otsun-2.14.0.dist-info/LICENSE.txt
otsun-2.14.0.dist-info/METADATA
otsun-2.14.0.dist-info/WHEEL
otsun-2.14.0.dist-info/RECORD
