Metadata-Version: 2.3
Name: otsun
Version: 2.14.0
Summary: 
Author: Biel Cardona
Author-email: bielcardona@gmail.com
Requires-Python: >=3.10
Classifier: Programming Language :: Python :: 3
Classifier: Programming Language :: Python :: 3.10
Classifier: Programming Language :: Python :: 3.11
Classifier: Programming Language :: Python :: 3.12
Classifier: Programming Language :: Python :: 3.13
Requires-Dist: autologging (>=1.3.2,<2.0.0)
Requires-Dist: numpy (>=1.23,<2.0)
Requires-Dist: pandas (>=1.5.2,<2.0.0)
Requires-Dist: scipy (>=1.9.3,<2.0.0)
Requires-Dist: toml (>=0.10.2,<0.11.0)
